ai/__init__.py
ai/chronon/__init__.py
ai/chronon/external_api.py
ai/chronon/group_by.py
ai/chronon/join.py
ai/chronon/logger.py
ai/chronon/model.py
ai/chronon/query.py
ai/chronon/staging_query.py
ai/chronon/utils.py
ai/chronon/api/__init__.py
ai/chronon/api/constants.py
ai/chronon/api/ttypes.py
ai/chronon/lineage/README.md
ai/chronon/lineage/__init__.py
ai/chronon/lineage/lineage_metadata.py
ai/chronon/lineage/lineage_parser.py
ai/chronon/repo/__init__.py
ai/chronon/repo/compile.py
ai/chronon/repo/dependency_tracker.py
ai/chronon/repo/explore.py
ai/chronon/repo/extract_objects.py
ai/chronon/repo/join_backfill.py
ai/chronon/repo/run.py
ai/chronon/repo/serializer.py
ai/chronon/repo/teams.py
ai/chronon/repo/validator.py
ai/chronon/scheduler/__init__.py
ai/chronon/scheduler/adapters/__init__.py
ai/chronon/scheduler/adapters/airflow_adapter.py
ai/chronon/scheduler/interfaces/__init__.py
ai/chronon/scheduler/interfaces/flow.py
ai/chronon/scheduler/interfaces/node.py
ai/chronon/scheduler/interfaces/orchestrator.py
ai/chronon/scheduler/utils/__init__.py
chronon_ai-0.0.109.data/scripts/compile.py
chronon_ai-0.0.109.data/scripts/explore.py
chronon_ai-0.0.109.data/scripts/run.py
chronon_ai-0.0.109.dist-info/licenses/LICENSE
chronon_ai-0.0.109.dist-info/METADATA
chronon_ai-0.0.109.dist-info/WHEEL
chronon_ai-0.0.109.dist-info/top_level.txt
chronon_ai-0.0.109.dist-info/RECORD
