Metadata-Version: 2.4
Name: chronon-ai
Version: 0.0.109
Summary: Chronon python API library
Classifier: Programming Language :: Python :: 3.7
Requires-Python: >=3.7
License-File: LICENSE
Requires-Dist: click
Requires-Dist: thrift<0.14
Requires-Dist: sqlglot
Provides-Extra: pip2compat
Requires-Dist: click<8; extra == "pip2compat"
Dynamic: classifier
Dynamic: description
Dynamic: description-content-type
Dynamic: license-file
Dynamic: provides-extra
Dynamic: requires-dist
Dynamic: requires-python
Dynamic: summary
